examples/__init__.py
examples/ml_agents.py
examples/ml_output_matcher.py
examples/ml_workflow.py
examples/visualization_example.py
taiat/__init__.py
taiat/base.py
taiat/builder.py
taiat/db.py
taiat/engine.py
taiat/example_usage.py
taiat/generic_matcher.py
taiat/manager.py
taiat/metrics.py
taiat/service.py
taiat/test_agent_registry.py
taiat/examples/agent_registry_example.py
taiat-0.0.2.dist-info/licenses/LICENSE
tests/__init__.py
tests/test_agents.py
tests/test_db.py
tests/test_graph.py
taiat-0.0.2.dist-info/METADATA
taiat-0.0.2.dist-info/WHEEL
taiat-0.0.2.dist-info/top_level.txt
taiat-0.0.2.dist-info/RECORD
