Metadata-Version: 2.4
Name: taiat
Version: 0.0.2
Summary: taiat is a tool for managing dependencies in AI agents
Author-email: Bill Pentney <wpentney2@gmail.com>
Project-URL: Homepage, https://github.com/pypa/taiat
Project-URL: Issues, https://github.com/pypa/taiat/issues
Classifier: Programming Language :: Python :: 3
Classifier: Operating System :: OS Independent
Classifier: License :: OSI Approved :: GNU General Public License v2 or later (GPLv2+)
Requires-Python: >=3.10
License-File: LICENSE
Dynamic: license-file
